<rules>
<service block="true" log="false">
    <component-filter name="com.google.android.gms/com.google.android.gms.ads.AdRequestBrokerService" />
    <component-filter name="com.google.android.gms/com.google.android.gms.ads.GservicesValueBrokerService" />
    <component-filter name="com.google.android.gms/com.google.android.gms.ads.cache.CacheBrokerService" />
    <component-filter name="com.google.android.gms/com.google.android.gms.ads.identifier.service.AdvertisingIdNotificationService" />
    <component-filter name="com.google.android.gms/com.google.android.gms.ads.identifier.service.AdvertisingIdService" />
    <component-filter name="com.google.android.gms/com.google.android.gms.ads.jams.NegotiationService" />
    <component-filter name="com.google.android.gms/com.google.android.gms.ads.measurement.AdsMeasurementBroadcastReceiver" />
    <component-filter name="com.google.android.gms/com.google.android.gms.ads.measurement.AdsMeasurementService" />
    <component-filter name="com.google.android.gms/com.google.android.gms.ads.measurement.GmpConversionTrackingBrokerService" />
    <component-filter name="com.google.android.gms/com.google.android.gms.ads.social.DoritosReceiver" />
    <component-filter name="com.google.android.gms/com.google.android.gms.ads.social.GcmSchedulerWakeupService" />
    <component-filter name="com.google.android.gms/com.google.android.gms.analytics.internal.PlayLogReportingService" />
    <component-filter name="com.google.android.gms/com.google.android.gms.analytics.service.AnalyticsService" />
    <component-filter name="com.google.android.gms/com.google.android.gms.analytics.service.PlayLogMonitorIntervalService" />
    <component-filter name="com.google.android.gms/com.google.android.gms.auth.account.authenticator.WorkAccountAuthenticatorService" />
    <component-filter name="com.google.android.gms/com.google.android.gms.auth.account.be.channelid.ChannelBindingStateIntentService" />
    <component-filter name="com.google.android.gms/com.google.android.gms.auth.uiflows.addaccount.DmDownloadInstallActivity" />
    <component-filter name="com.google.android.gms/com.google.android.gms.autofill.service.AutofillService" />
    <component-filter name="com.google.android.gms/com.google.android.gms.autofill.ui.AutofillActivity" />
    <component-filter name="com.google.android.gms/com.google.android.gms.autofill.ui.AutofillDialogActivity" />
    <component-filter name="com.google.android.gms/com.google.android.gms.autofill.ui.AutofillSettingsActivity" />
    <component-filter name="com.google.android.gms/com.google.android.gms.backup.component.BackupOptInActivity" />
    <component-filter name="com.google.android.gms/com.google.android.gms.backup.component.D2dMigrateFlowActivity" />
    <component-filter name="com.google.android.gms/com.google.android.gms.backup.component.D2dMigrateHelperService" />
    <component-filter name="com.google.android.gms/com.google.android.gms.backup.component.D2dMigrateService" />
    <component-filter name="com.google.android.gms/com.google.android.gms.backup.component.D2dPreLSourceActivity" />
    <component-filter name="com.google.android.gms/com.google.android.gms.backup.component.D2dTransportService" />
    <component-filter name="com.google.android.gms/com.google.android.gms.backup.component.EmmRestoreFlowActivity" />
    <component-filter name="com.google.android.gms/com.google.android.gms.backup.component.RestoreSessionV0Service" />
    <component-filter name="com.google.android.gms/com.google.android.gms.backup.component.UsbDeviceAttachedActivity" />
    <component-filter name="com.google.android.gms/com.google.android.gms.checkin.CheckinServiceActiveReceiver" />
    <component-filter name="com.google.android.gms/com.google.android.gms.common.analytics.CoreAnalyticsAlarmReceiver" />
    <component-filter name="com.google.android.gms/com.google.android.gms.feedback.LegacyBugReportService" />
    <component-filter name="com.google.android.gms/com.google.android.gms.games.chimera.GamesAndroidServiceProxy" />
    <component-filter name="com.google.android.gms/com.google.android.gms.games.chimera.GamesAsyncServiceProxy" />
    <component-filter name="com.google.android.gms/com.google.android.gms.games.chimera.GamesSignInIntentServiceProxy" />
    <component-filter name="com.google.android.gms/com.google.android.gms.games.chimera.GamesSignInServiceProxy" />
    <component-filter name="com.google.android.gms/com.google.android.gms.games.chimera.GamesSyncServiceMainProxy" />
    <component-filter name="com.google.android.gms/com.google.android.gms.games.chimera.GamesSyncServiceNotificationProxy" />
    <component-filter name="com.google.android.gms/com.google.android.gms.games.chimera.GamesUploadServiceProxy" />
    <component-filter name="com.google.android.gms/com.google.android.gms.games.chimera.RoomAndroidServiceProxy" />
    <component-filter name="com.google.android.gms/com.google.android.gms.games.chimera.SnapshotEventServiceProxy" />
    <component-filter name="com.google.android.gms/com.google.android.gms.mdm.receivers.AccountsChangedReceiver" />
    <component-filter name="com.google.android.gms/com.google.android.gms.mdm.receivers.ConnectivityReceiver" />
    <component-filter name="com.google.android.gms/com.google.android.gms.netrec.scoring.receiver.ScoreNetworksBroadcastReceiver" />
    <component-filter name="com.google.android.gms/com.google.android.gms.ocr.CardCaptureActivity" />
    <component-filter name="com.google.android.gms/com.google.android.gms.ocr.GiftCardOcrActivity" />
    <component-filter name="com.google.android.gms/com.google.android.gms.ocr.SecuredCreditCardOcrActivity" />
    <component-filter name="com.google.android.gms/com.google.android.gms.people.pub.PeopleProfileActionGatewayActivity" />
    <component-filter name="com.google.android.gms/com.google.android.gms.playlog.uploader.UploaderIntentService" />
    <component-filter name="com.google.android.gms/com.google.android.gms.trustagent.GoogleTrustAgentTrustStatusMonitorSetting" />
    <component-filter name="com.google.android.gms/com.google.android.gms.update.SystemUpdateServiceActiveReceiver" />
    <component-filter name="com.google.android.gms/com.google.android.gms.update.SystemUpdateService\$ActiveReceiver" />
    <component-filter name="com.google.android.gms/com.google.android.gms.wallet.service.CrashReportIntentService" />
    <component-filter name="com.google.android.gms/com.google.android.gms.wallet.service.analytics.AnalyticsIntentService" />
</service>
<broadcast block="true" log="false">
    <component-filter name="com.google.android.gms/com.google.android.gms.ads.AdRequestBrokerService" />
    <component-filter name="com.google.android.gms/com.google.android.gms.ads.GservicesValueBrokerService" />
    <component-filter name="com.google.android.gms/com.google.android.gms.ads.cache.CacheBrokerService" />
    <component-filter name="com.google.android.gms/com.google.android.gms.ads.identifier.service.AdvertisingIdNotificationService" />
    <component-filter name="com.google.android.gms/com.google.android.gms.ads.identifier.service.AdvertisingIdService" />
    <component-filter name="com.google.android.gms/com.google.android.gms.ads.jams.NegotiationService" />
    <component-filter name="com.google.android.gms/com.google.android.gms.ads.measurement.AdsMeasurementBroadcastReceiver" />
    <component-filter name="com.google.android.gms/com.google.android.gms.ads.measurement.AdsMeasurementService" />
    <component-filter name="com.google.android.gms/com.google.android.gms.ads.measurement.GmpConversionTrackingBrokerService" />
    <component-filter name="com.google.android.gms/com.google.android.gms.ads.social.DoritosReceiver" />
    <component-filter name="com.google.android.gms/com.google.android.gms.ads.social.GcmSchedulerWakeupService" />
    <component-filter name="com.google.android.gms/com.google.android.gms.analytics.internal.PlayLogReportingService" />
    <component-filter name="com.google.android.gms/com.google.android.gms.analytics.service.AnalyticsService" />
    <component-filter name="com.google.android.gms/com.google.android.gms.analytics.service.PlayLogMonitorIntervalService" />
    <component-filter name="com.google.android.gms/com.google.android.gms.auth.account.authenticator.WorkAccountAuthenticatorService" />
    <component-filter name="com.google.android.gms/com.google.android.gms.auth.account.be.channelid.ChannelBindingStateIntentService" />
    <component-filter name="com.google.android.gms/com.google.android.gms.auth.uiflows.addaccount.DmDownloadInstallActivity" />
    <component-filter name="com.google.android.gms/com.google.android.gms.autofill.service.AutofillService" />
    <component-filter name="com.google.android.gms/com.google.android.gms.autofill.ui.AutofillActivity" />
    <component-filter name="com.google.android.gms/com.google.android.gms.autofill.ui.AutofillDialogActivity" />
    <component-filter name="com.google.android.gms/com.google.android.gms.autofill.ui.AutofillSettingsActivity" />
    <component-filter name="com.google.android.gms/com.google.android.gms.backup.component.BackupOptInActivity" />
    <component-filter name="com.google.android.gms/com.google.android.gms.backup.component.D2dMigrateFlowActivity" />
    <component-filter name="com.google.android.gms/com.google.android.gms.backup.component.D2dMigrateHelperService" />
    <component-filter name="com.google.android.gms/com.google.android.gms.backup.component.D2dMigrateService" />
    <component-filter name="com.google.android.gms/com.google.android.gms.backup.component.D2dPreLSourceActivity" />
    <component-filter name="com.google.android.gms/com.google.android.gms.backup.component.D2dTransportService" />
    <component-filter name="com.google.android.gms/com.google.android.gms.backup.component.EmmRestoreFlowActivity" />
    <component-filter name="com.google.android.gms/com.google.android.gms.backup.component.RestoreSessionV0Service" />
    <component-filter name="com.google.android.gms/com.google.android.gms.backup.component.UsbDeviceAttachedActivity" />
    <component-filter name="com.google.android.gms/com.google.android.gms.checkin.CheckinServiceActiveReceiver" />
    <component-filter name="com.google.android.gms/com.google.android.gms.common.analytics.CoreAnalyticsAlarmReceiver" />
    <component-filter name="com.google.android.gms/com.google.android.gms.feedback.LegacyBugReportService" />
    <component-filter name="com.google.android.gms/com.google.android.gms.games.chimera.GamesAndroidServiceProxy" />
    <component-filter name="com.google.android.gms/com.google.android.gms.games.chimera.GamesAsyncServiceProxy" />
    <component-filter name="com.google.android.gms/com.google.android.gms.games.chimera.GamesSignInIntentServiceProxy" />
    <component-filter name="com.google.android.gms/com.google.android.gms.games.chimera.GamesSignInServiceProxy" />
    <component-filter name="com.google.android.gms/com.google.android.gms.games.chimera.GamesSyncServiceMainProxy" />
    <component-filter name="com.google.android.gms/com.google.android.gms.games.chimera.GamesSyncServiceNotificationProxy" />
    <component-filter name="com.google.android.gms/com.google.android.gms.games.chimera.GamesUploadServiceProxy" />
    <component-filter name="com.google.android.gms/com.google.android.gms.games.chimera.RoomAndroidServiceProxy" />
    <component-filter name="com.google.android.gms/com.google.android.gms.games.chimera.SnapshotEventServiceProxy" />
    <component-filter name="com.google.android.gms/com.google.android.gms.mdm.receivers.AccountsChangedReceiver" />
    <component-filter name="com.google.android.gms/com.google.android.gms.mdm.receivers.ConnectivityReceiver" />
    <component-filter name="com.google.android.gms/com.google.android.gms.netrec.scoring.receiver.ScoreNetworksBroadcastReceiver" />
    <component-filter name="com.google.android.gms/com.google.android.gms.ocr.CardCaptureActivity" />
    <component-filter name="com.google.android.gms/com.google.android.gms.ocr.GiftCardOcrActivity" />
    <component-filter name="com.google.android.gms/com.google.android.gms.ocr.SecuredCreditCardOcrActivity" />
    <component-filter name="com.google.android.gms/com.google.android.gms.people.pub.PeopleProfileActionGatewayActivity" />
    <component-filter name="com.google.android.gms/com.google.android.gms.playlog.uploader.UploaderIntentService" />
    <component-filter name="com.google.android.gms/com.google.android.gms.trustagent.GoogleTrustAgentTrustStatusMonitorSetting" />
    <component-filter name="com.google.android.gms/com.google.android.gms.update.SystemUpdateServiceActiveReceiver" />
    <component-filter name="com.google.android.gms/com.google.android.gms.update.SystemUpdateService\$ActiveReceiver" />
    <component-filter name="com.google.android.gms/com.google.android.gms.wallet.service.CrashReportIntentService" />
    <component-filter name="com.google.android.gms/com.google.android.gms.wallet.service.analytics.AnalyticsIntentService" />
</broadcast>
<activity block="true" log="false">
    <component-filter name="com.google.android.gms/com.google.android.gms.ads.AdRequestBrokerService" />
    <component-filter name="com.google.android.gms/com.google.android.gms.ads.GservicesValueBrokerService" />
    <component-filter name="com.google.android.gms/com.google.android.gms.ads.cache.CacheBrokerService" />
    <component-filter name="com.google.android.gms/com.google.android.gms.ads.identifier.service.AdvertisingIdNotificationService" />
    <component-filter name="com.google.android.gms/com.google.android.gms.ads.identifier.service.AdvertisingIdService" />
    <component-filter name="com.google.android.gms/com.google.android.gms.ads.jams.NegotiationService" />
    <component-filter name="com.google.android.gms/com.google.android.gms.ads.measurement.AdsMeasurementBroadcastReceiver" />
    <component-filter name="com.google.android.gms/com.google.android.gms.ads.measurement.AdsMeasurementService" />
    <component-filter name="com.google.android.gms/com.google.android.gms.ads.measurement.GmpConversionTrackingBrokerService" />
    <component-filter name="com.google.android.gms/com.google.android.gms.ads.social.DoritosReceiver" />
    <component-filter name="com.google.android.gms/com.google.android.gms.ads.social.GcmSchedulerWakeupService" />
    <component-filter name="com.google.android.gms/com.google.android.gms.analytics.internal.PlayLogReportingService" />
    <component-filter name="com.google.android.gms/com.google.android.gms.analytics.service.AnalyticsService" />
    <component-filter name="com.google.android.gms/com.google.android.gms.analytics.service.PlayLogMonitorIntervalService" />
    <component-filter name="com.google.android.gms/com.google.android.gms.auth.account.authenticator.WorkAccountAuthenticatorService" />
    <component-filter name="com.google.android.gms/com.google.android.gms.auth.account.be.channelid.ChannelBindingStateIntentService" />
    <component-filter name="com.google.android.gms/com.google.android.gms.auth.uiflows.addaccount.DmDownloadInstallActivity" />
    <component-filter name="com.google.android.gms/com.google.android.gms.autofill.service.AutofillService" />
    <component-filter name="com.google.android.gms/com.google.android.gms.autofill.ui.AutofillActivity" />
    <component-filter name="com.google.android.gms/com.google.android.gms.autofill.ui.AutofillDialogActivity" />
    <component-filter name="com.google.android.gms/com.google.android.gms.autofill.ui.AutofillSettingsActivity" />
    <component-filter name="com.google.android.gms/com.google.android.gms.backup.component.BackupOptInActivity" />
    <component-filter name="com.google.android.gms/com.google.android.gms.backup.component.D2dMigrateFlowActivity" />
    <component-filter name="com.google.android.gms/com.google.android.gms.backup.component.D2dMigrateHelperService" />
    <component-filter name="com.google.android.gms/com.google.android.gms.backup.component.D2dMigrateService" />
    <component-filter name="com.google.android.gms/com.google.android.gms.backup.component.D2dPreLSourceActivity" />
    <component-filter name="com.google.android.gms/com.google.android.gms.backup.component.D2dTransportService" />
    <component-filter name="com.google.android.gms/com.google.android.gms.backup.component.EmmRestoreFlowActivity" />
    <component-filter name="com.google.android.gms/com.google.android.gms.backup.component.RestoreSessionV0Service" />
    <component-filter name="com.google.android.gms/com.google.android.gms.backup.component.UsbDeviceAttachedActivity" />
    <component-filter name="com.google.android.gms/com.google.android.gms.checkin.CheckinServiceActiveReceiver" />
    <component-filter name="com.google.android.gms/com.google.android.gms.common.analytics.CoreAnalyticsAlarmReceiver" />
    <component-filter name="com.google.android.gms/com.google.android.gms.feedback.LegacyBugReportService" />
    <component-filter name="com.google.android.gms/com.google.android.gms.games.chimera.GamesAndroidServiceProxy" />
    <component-filter name="com.google.android.gms/com.google.android.gms.games.chimera.GamesAsyncServiceProxy" />
    <component-filter name="com.google.android.gms/com.google.android.gms.games.chimera.GamesSignInIntentServiceProxy" />
    <component-filter name="com.google.android.gms/com.google.android.gms.games.chimera.GamesSignInServiceProxy" />
    <component-filter name="com.google.android.gms/com.google.android.gms.games.chimera.GamesSyncServiceMainProxy" />
    <component-filter name="com.google.android.gms/com.google.android.gms.games.chimera.GamesSyncServiceNotificationProxy" />
    <component-filter name="com.google.android.gms/com.google.android.gms.games.chimera.GamesUploadServiceProxy" />
    <component-filter name="com.google.android.gms/com.google.android.gms.games.chimera.RoomAndroidServiceProxy" />
    <component-filter name="com.google.android.gms/com.google.android.gms.games.chimera.SnapshotEventServiceProxy" />
    <component-filter name="com.google.android.gms/com.google.android.gms.mdm.receivers.AccountsChangedReceiver" />
    <component-filter name="com.google.android.gms/com.google.android.gms.mdm.receivers.ConnectivityReceiver" />
    <component-filter name="com.google.android.gms/com.google.android.gms.netrec.scoring.receiver.ScoreNetworksBroadcastReceiver" />
    <component-filter name="com.google.android.gms/com.google.android.gms.ocr.CardCaptureActivity" />
    <component-filter name="com.google.android.gms/com.google.android.gms.ocr.GiftCardOcrActivity" />
    <component-filter name="com.google.android.gms/com.google.android.gms.ocr.SecuredCreditCardOcrActivity" />
    <component-filter name="com.google.android.gms/com.google.android.gms.people.pub.PeopleProfileActionGatewayActivity" />
    <component-filter name="com.google.android.gms/com.google.android.gms.playlog.uploader.UploaderIntentService" />
    <component-filter name="com.google.android.gms/com.google.android.gms.trustagent.GoogleTrustAgentTrustStatusMonitorSetting" />
    <component-filter name="com.google.android.gms/com.google.android.gms.update.SystemUpdateServiceActiveReceiver" />
    <component-filter name="com.google.android.gms/com.google.android.gms.update.SystemUpdateService\$ActiveReceiver" />
    <component-filter name="com.google.android.gms/com.google.android.gms.wallet.service.CrashReportIntentService" />
    <component-filter name="com.google.android.gms/com.google.android.gms.wallet.service.analytics.AnalyticsIntentService" />
</activity>
</rules>