<rules>
<service block="true" log="false">
    <component-filter name="com.tencent.mm/com.tencent.mm.booter.InstallReceiver" />
    <component-filter name="com.tencent.mm/com.tencent.mm.booter.cache.CacheService" />
    <component-filter name="com.tencent.mm/com.tencent.mm.crash.CrashUploaderService" />
    <component-filter name="com.tencent.mm/com.tencent.mm.modelfriend.AddrBookObserver$AddrBookService" />
    <component-filter name="com.tencent.mm/com.tencent.mm.plugin.accountsync.model.AccountAuthenticatorService" />
    <component-filter name="com.tencent.mm/com.tencent.mm.plugin.accountsync.model.ContactsSyncService" />
    <component-filter name="com.tencent.mm/com.tencent.mm.plugin.accountsync.ui.ShareToFacebookRedirectUI" />
    <component-filter name="com.tencent.mm/com.tencent.mm.plugin.appbrand.task.AppBrandTaskPreloadReceiver" />
    <component-filter name="com.tencent.mm/com.tencent.mm.plugin.appbrand.task.AppBrandTaskPreloadReceiver1" />
    <component-filter name="com.tencent.mm/com.tencent.mm.plugin.appbrand.task.AppBrandTaskPreloadReceiver2" />
    <component-filter name="com.tencent.mm/com.tencent.mm.plugin.appbrand.task.AppBrandTaskPreloadReceiver3" />
    <component-filter name="com.tencent.mm/com.tencent.mm.plugin.appbrand.task.AppBrandTaskPreloadReceiver4" />
    <component-filter name="com.tencent.mm/com.tencent.mm.plugin.backup.backuppcmodel.BackupPcService" />
    <component-filter name="com.tencent.mm/com.tencent.mm.plugin.backup.bakoldlogic.bakoldmodel.BakOldUSBService" />
    <component-filter name="com.tencent.mm/com.tencent.mm.plugin.backup.bakoldlogic.bakoldmovemodel.MoveService" />
    <component-filter name="com.tencent.mm/com.tencent.mm.plugin.backup.bakoldlogic.bakoldpcmodel.BakchatPcUsbService" />
    <component-filter name="com.tencent.mm/com.tencent.mm.plugin.exdevice.ui.ExdeviceConnectWifiUI" />
    <component-filter name="com.tencent.mm/com.tencent.mm.plugin.facedetect.service.FaceDetectProcessService" />
    <component-filter name="com.tencent.mm/com.tencent.mm.plugin.facedetect.service.FaceUploadVideoService" />
    <component-filter name="com.tencent.mm/com.tencent.mm.plugin.freewifi.ui.FreeWifiActivateAuthStateUI" />
    <component-filter name="com.tencent.mm/com.tencent.mm.plugin.freewifi.ui.FreeWifiAuthStateUI" />
    <component-filter name="com.tencent.mm/com.tencent.mm.plugin.freewifi.ui.FreeWifiCopyPwdUI" />
    <component-filter name="com.tencent.mm/com.tencent.mm.plugin.freewifi.ui.FreeWifiEntryUI" />
    <component-filter name="com.tencent.mm/com.tencent.mm.plugin.freewifi.ui.FreeWifiErrorUI" />
    <component-filter name="com.tencent.mm/com.tencent.mm.plugin.freewifi.ui.FreeWifiFrontPageUI" />
    <component-filter name="com.tencent.mm/com.tencent.mm.plugin.freewifi.ui.FreeWifiIntroductionUI" />
    <component-filter name="com.tencent.mm/com.tencent.mm.plugin.freewifi.ui.FreeWifiMIGNoAuthStateUI" />
    <component-filter name="com.tencent.mm/com.tencent.mm.plugin.freewifi.ui.FreeWifiManufacturerLoadingUI" />
    <component-filter name="com.tencent.mm/com.tencent.mm.plugin.freewifi.ui.FreeWifiNetCheckUI" />
    <component-filter name="com.tencent.mm/com.tencent.mm.plugin.freewifi.ui.FreeWifiNoWifiUI" />
    <component-filter name="com.tencent.mm/com.tencent.mm.plugin.freewifi.ui.FreeWifiOwnerUI" />
    <component-filter name="com.tencent.mm/com.tencent.mm.plugin.freewifi.ui.FreeWifiPcUI" />
    <component-filter name="com.tencent.mm/com.tencent.mm.plugin.freewifi.ui.FreeWifiSuccUI" />
    <component-filter name="com.tencent.mm/com.tencent.mm.plugin.freewifi.ui.FreeWifiSuccWebViewUI" />
    <component-filter name="com.tencent.mm/com.tencent.mm.plugin.freewifi.ui.FreeWifiTestActivity" />
    <component-filter name="com.tencent.mm/com.tencent.mm.plugin.freewifi.ui.FreewifiActivateWeChatNoAuthStateUI" />
    <component-filter name="com.tencent.mm/com.tencent.mm.plugin.freewifi.ui.FreewifiWeChatNoAuthStateUI" />
    <component-filter name="com.tencent.mm/com.tencent.mm.plugin.freewifi.ui.ProtocolThreeOneUI" />
    <component-filter name="com.tencent.mm/com.tencent.mm.plugin.freewifi.ui.ProtocolThreeThreeUI" />
    <component-filter name="com.tencent.mm/com.tencent.mm.plugin.freewifi.ui.ProtocolThreeTwoUI" />
    <component-filter name="com.tencent.mm/com.tencent.mm.plugin.game.gamewebview.ipc.GameWebViewMainProcessService" />
    <component-filter name="com.tencent.mm/com.tencent.mm.plugin.game.gamewebview.ui.GameIpcProxyUI" />
    <component-filter name="com.tencent.mm/com.tencent.mm.plugin.game.gamewebview.ui.GameWebViewUI" />
    <component-filter name="com.tencent.mm/com.tencent.mm.plugin.game.ui.AuthorizedGameListUI" />
    <component-filter name="com.tencent.mm/com.tencent.mm.plugin.game.ui.CreateOrJoinChatroomUI" />
    <component-filter name="com.tencent.mm/com.tencent.mm.plugin.game.ui.GameCategoryUI" />
    <component-filter name="com.tencent.mm/com.tencent.mm.plugin.game.ui.GameCenterUI" />
    <component-filter name="com.tencent.mm/com.tencent.mm.plugin.game.ui.GameCenterUI2" />
    <component-filter name="com.tencent.mm/com.tencent.mm.plugin.game.ui.GameDetailInfoUI" />
    <component-filter name="com.tencent.mm/com.tencent.mm.plugin.game.ui.GameDetailRankLikedUI" />
    <component-filter name="com.tencent.mm/com.tencent.mm.plugin.game.ui.GameDetailRankUI" />
    <component-filter name="com.tencent.mm/com.tencent.mm.plugin.game.ui.GameDetailUI" />
    <component-filter name="com.tencent.mm/com.tencent.mm.plugin.game.ui.GameDetailUI2" />
    <component-filter name="com.tencent.mm/com.tencent.mm.plugin.game.ui.GameDownloadTipsUI" />
    <component-filter name="com.tencent.mm/com.tencent.mm.plugin.game.ui.GameGalleryUI" />
    <component-filter name="com.tencent.mm/com.tencent.mm.plugin.game.ui.GameGestureGalleryUI" />
    <component-filter name="com.tencent.mm/com.tencent.mm.plugin.game.ui.GameIndexUI" />
    <component-filter name="com.tencent.mm/com.tencent.mm.plugin.game.ui.GameLibraryUI" />
    <component-filter name="com.tencent.mm/com.tencent.mm.plugin.game.ui.GameMD5CheckUI" />
    <component-filter name="com.tencent.mm/com.tencent.mm.plugin.game.ui.GameMessageUI" />
    <component-filter name="com.tencent.mm/com.tencent.mm.plugin.game.ui.GameNewIntroductionUI" />
    <component-filter name="com.tencent.mm/com.tencent.mm.plugin.game.ui.GameRankMsgUI" />
    <component-filter name="com.tencent.mm/com.tencent.mm.plugin.game.ui.GameRankUI" />
    <component-filter name="com.tencent.mm/com.tencent.mm.plugin.game.ui.GameRegionSelectUI" />
    <component-filter name="com.tencent.mm/com.tencent.mm.plugin.game.ui.GameSearchUI" />
    <component-filter name="com.tencent.mm/com.tencent.mm.plugin.game.ui.GameSettingsUI" />
    <component-filter name="com.tencent.mm/com.tencent.mm.plugin.qqmail.stub.QQMailStubProxyUI" />
    <component-filter name="com.tencent.mm/com.tencent.mm.plugin.qqmail.ui.AttachDownloadPage" />
    <component-filter name="com.tencent.mm/com.tencent.mm.plugin.qqmail.ui.ComposeUI" />
    <component-filter name="com.tencent.mm/com.tencent.mm.plugin.qqmail.ui.CompressPreviewUI" />
    <component-filter name="com.tencent.mm/com.tencent.mm.plugin.qqmail.ui.MailAddrListUI" />
    <component-filter name="com.tencent.mm/com.tencent.mm.plugin.qqmail.ui.MailAddrProfileUI" />
    <component-filter name="com.tencent.mm/com.tencent.mm.plugin.qqmail.ui.MailImageDownloadUI" />
    <component-filter name="com.tencent.mm/com.tencent.mm.plugin.qqmail.ui.MailWebViewUI" />
    <component-filter name="com.tencent.mm/com.tencent.mm.plugin.qqmail.ui.ReadMailUI" />
    <component-filter name="com.tencent.mm/com.tencent.mm.plugin.shake.shakemedia.ui.ShakeTVDetailUI" />
    <component-filter name="com.tencent.mm/com.tencent.mm.plugin.shake.ui.ShakeItemListUI" />
    <component-filter name="com.tencent.mm/com.tencent.mm.plugin.shake.ui.ShakeMsgListUI" />
    <component-filter name="com.tencent.mm/com.tencent.mm.plugin.shake.ui.ShakeNewYearReportUI" />
    <component-filter name="com.tencent.mm/com.tencent.mm.plugin.shake.ui.ShakePersonalInfoUI" />
    <component-filter name="com.tencent.mm/com.tencent.mm.plugin.shake.ui.ShakeReportUI" />
    <component-filter name="com.tencent.mm/com.tencent.mm.plugin.shake.ui.ShakeSayHiListUI" />
    <component-filter name="com.tencent.mm/com.tencent.mm.plugin.shake.ui.ShakeTvHistoryListUI" />
    <component-filter name="com.tencent.mm/com.tencent.mm.plugin.shake.ui.TVInfoUI" />
    <component-filter name="com.tencent.mm/com.tencent.mm.plugin.sport.service.SportService" />
    <component-filter name="com.tencent.mm/com.tencent.mm.plugin.subapp.jdbiz.JDRemindDialog" />
    <component-filter name="com.tencent.mm/com.tencent.mm.plugin.wear.model.service.WearDataLayerService" />
    <component-filter name="com.tencent.mm/com.tencent.mm.plugin.webview.ui.tools.game.GameChattingRoomWebViewUI" />
    <component-filter name="com.tencent.mm/com.tencent.mm.plugin.webview.ui.tools.game.GameWebViewUI" />
    <component-filter name="com.tencent.mm/com.tencent.mm.plugin.webview.ui.tools.game.H5GameWebViewUI" />
    <component-filter name="com.tencent.mm/com.tencent.mm.sandbox.monitor.CrashUploadAlarmReceiver" />
    <component-filter name="com.tencent.mm/com.tencent.mm.sandbox.updater.AppInstallerUI" />
    <component-filter name="com.tencent.mm/com.tencent.mm.sandbox.updater.AppUpdaterUI" />
    <component-filter name="com.tencent.mm/com.tencent.mm.sandbox.updater.UpdaterService" />
    <component-filter name="com.tencent.mm/com.tencent.mm.ui.account.BindFacebookUI" />
    <component-filter name="com.tencent.mm/com.tencent.mm.ui.account.FacebookAuthUI" />
    <component-filter name="com.tencent.mm/com.tencent.mm.ui.account.FacebookFriendUI" />
    <component-filter name="com.tencent.mm/com.tencent.mm.ui.account.FacebookLoginUI" />
    <component-filter name="com.tencent.mm/com.tencent.mm.ui.account.RegByFacebookSetPwdUI" />
    <component-filter name="com.tencent.mm/com.tencent.mm.ui.bindgooglecontact.BindGoogleContactIntroUI" />
    <component-filter name="com.tencent.mm/com.tencent.mm.ui.bindgooglecontact.BindGoogleContactUI" />
    <component-filter name="com.tencent.mm/com.tencent.mm.ui.bindgooglecontact.GoogleFriendUI" />
    <component-filter name="com.tencent.mm/com.tencent.mm.ui.bindlinkedin.BindLinkedInUI" />
    <component-filter name="com.tencent.mm/com.tencent.mm.ui.friend.InviteFacebookFriendsUI" />
    <component-filter name="com.tencent.mm/com.tencent.recovery.wx.service.WXRecoveryUploadService" />
    <component-filter name="com.tencent.mm/com.tencent.tmassistantsdk.downloadservice.TMAssistantDownloadSDKService" />
    <component-filter name="com.xiaomi.o2o/com.tencent.mm.sdk.channel.MMessage$Receiver" />
    <component-filter name="com.xiaomi.o2o/com.tencent.mm.sdk.plugin.MMPluginOAuth$Receiver" />
</service>
<broadcast block="true" log="false">
    <component-filter name="com.tencent.mm/com.tencent.mm.booter.InstallReceiver" />
    <component-filter name="com.tencent.mm/com.tencent.mm.booter.cache.CacheService" />
    <component-filter name="com.tencent.mm/com.tencent.mm.crash.CrashUploaderService" />
    <component-filter name="com.tencent.mm/com.tencent.mm.modelfriend.AddrBookObserver$AddrBookService" />
    <component-filter name="com.tencent.mm/com.tencent.mm.plugin.accountsync.model.AccountAuthenticatorService" />
    <component-filter name="com.tencent.mm/com.tencent.mm.plugin.accountsync.model.ContactsSyncService" />
    <component-filter name="com.tencent.mm/com.tencent.mm.plugin.accountsync.ui.ShareToFacebookRedirectUI" />
    <component-filter name="com.tencent.mm/com.tencent.mm.plugin.appbrand.task.AppBrandTaskPreloadReceiver" />
    <component-filter name="com.tencent.mm/com.tencent.mm.plugin.appbrand.task.AppBrandTaskPreloadReceiver1" />
    <component-filter name="com.tencent.mm/com.tencent.mm.plugin.appbrand.task.AppBrandTaskPreloadReceiver2" />
    <component-filter name="com.tencent.mm/com.tencent.mm.plugin.appbrand.task.AppBrandTaskPreloadReceiver3" />
    <component-filter name="com.tencent.mm/com.tencent.mm.plugin.appbrand.task.AppBrandTaskPreloadReceiver4" />
    <component-filter name="com.tencent.mm/com.tencent.mm.plugin.backup.backuppcmodel.BackupPcService" />
    <component-filter name="com.tencent.mm/com.tencent.mm.plugin.backup.bakoldlogic.bakoldmodel.BakOldUSBService" />
    <component-filter name="com.tencent.mm/com.tencent.mm.plugin.backup.bakoldlogic.bakoldmovemodel.MoveService" />
    <component-filter name="com.tencent.mm/com.tencent.mm.plugin.backup.bakoldlogic.bakoldpcmodel.BakchatPcUsbService" />
    <component-filter name="com.tencent.mm/com.tencent.mm.plugin.exdevice.ui.ExdeviceConnectWifiUI" />
    <component-filter name="com.tencent.mm/com.tencent.mm.plugin.facedetect.service.FaceDetectProcessService" />
    <component-filter name="com.tencent.mm/com.tencent.mm.plugin.facedetect.service.FaceUploadVideoService" />
    <component-filter name="com.tencent.mm/com.tencent.mm.plugin.freewifi.ui.FreeWifiActivateAuthStateUI" />
    <component-filter name="com.tencent.mm/com.tencent.mm.plugin.freewifi.ui.FreeWifiAuthStateUI" />
    <component-filter name="com.tencent.mm/com.tencent.mm.plugin.freewifi.ui.FreeWifiCopyPwdUI" />
    <component-filter name="com.tencent.mm/com.tencent.mm.plugin.freewifi.ui.FreeWifiEntryUI" />
    <component-filter name="com.tencent.mm/com.tencent.mm.plugin.freewifi.ui.FreeWifiErrorUI" />
    <component-filter name="com.tencent.mm/com.tencent.mm.plugin.freewifi.ui.FreeWifiFrontPageUI" />
    <component-filter name="com.tencent.mm/com.tencent.mm.plugin.freewifi.ui.FreeWifiIntroductionUI" />
    <component-filter name="com.tencent.mm/com.tencent.mm.plugin.freewifi.ui.FreeWifiMIGNoAuthStateUI" />
    <component-filter name="com.tencent.mm/com.tencent.mm.plugin.freewifi.ui.FreeWifiManufacturerLoadingUI" />
    <component-filter name="com.tencent.mm/com.tencent.mm.plugin.freewifi.ui.FreeWifiNetCheckUI" />
    <component-filter name="com.tencent.mm/com.tencent.mm.plugin.freewifi.ui.FreeWifiNoWifiUI" />
    <component-filter name="com.tencent.mm/com.tencent.mm.plugin.freewifi.ui.FreeWifiOwnerUI" />
    <component-filter name="com.tencent.mm/com.tencent.mm.plugin.freewifi.ui.FreeWifiPcUI" />
    <component-filter name="com.tencent.mm/com.tencent.mm.plugin.freewifi.ui.FreeWifiSuccUI" />
    <component-filter name="com.tencent.mm/com.tencent.mm.plugin.freewifi.ui.FreeWifiSuccWebViewUI" />
    <component-filter name="com.tencent.mm/com.tencent.mm.plugin.freewifi.ui.FreeWifiTestActivity" />
    <component-filter name="com.tencent.mm/com.tencent.mm.plugin.freewifi.ui.FreewifiActivateWeChatNoAuthStateUI" />
    <component-filter name="com.tencent.mm/com.tencent.mm.plugin.freewifi.ui.FreewifiWeChatNoAuthStateUI" />
    <component-filter name="com.tencent.mm/com.tencent.mm.plugin.freewifi.ui.ProtocolThreeOneUI" />
    <component-filter name="com.tencent.mm/com.tencent.mm.plugin.freewifi.ui.ProtocolThreeThreeUI" />
    <component-filter name="com.tencent.mm/com.tencent.mm.plugin.freewifi.ui.ProtocolThreeTwoUI" />
    <component-filter name="com.tencent.mm/com.tencent.mm.plugin.game.gamewebview.ipc.GameWebViewMainProcessService" />
    <component-filter name="com.tencent.mm/com.tencent.mm.plugin.game.gamewebview.ui.GameIpcProxyUI" />
    <component-filter name="com.tencent.mm/com.tencent.mm.plugin.game.gamewebview.ui.GameWebViewUI" />
    <component-filter name="com.tencent.mm/com.tencent.mm.plugin.game.ui.AuthorizedGameListUI" />
    <component-filter name="com.tencent.mm/com.tencent.mm.plugin.game.ui.CreateOrJoinChatroomUI" />
    <component-filter name="com.tencent.mm/com.tencent.mm.plugin.game.ui.GameCategoryUI" />
    <component-filter name="com.tencent.mm/com.tencent.mm.plugin.game.ui.GameCenterUI" />
    <component-filter name="com.tencent.mm/com.tencent.mm.plugin.game.ui.GameCenterUI2" />
    <component-filter name="com.tencent.mm/com.tencent.mm.plugin.game.ui.GameDetailInfoUI" />
    <component-filter name="com.tencent.mm/com.tencent.mm.plugin.game.ui.GameDetailRankLikedUI" />
    <component-filter name="com.tencent.mm/com.tencent.mm.plugin.game.ui.GameDetailRankUI" />
    <component-filter name="com.tencent.mm/com.tencent.mm.plugin.game.ui.GameDetailUI" />
    <component-filter name="com.tencent.mm/com.tencent.mm.plugin.game.ui.GameDetailUI2" />
    <component-filter name="com.tencent.mm/com.tencent.mm.plugin.game.ui.GameDownloadTipsUI" />
    <component-filter name="com.tencent.mm/com.tencent.mm.plugin.game.ui.GameGalleryUI" />
    <component-filter name="com.tencent.mm/com.tencent.mm.plugin.game.ui.GameGestureGalleryUI" />
    <component-filter name="com.tencent.mm/com.tencent.mm.plugin.game.ui.GameIndexUI" />
    <component-filter name="com.tencent.mm/com.tencent.mm.plugin.game.ui.GameLibraryUI" />
    <component-filter name="com.tencent.mm/com.tencent.mm.plugin.game.ui.GameMD5CheckUI" />
    <component-filter name="com.tencent.mm/com.tencent.mm.plugin.game.ui.GameMessageUI" />
    <component-filter name="com.tencent.mm/com.tencent.mm.plugin.game.ui.GameNewIntroductionUI" />
    <component-filter name="com.tencent.mm/com.tencent.mm.plugin.game.ui.GameRankMsgUI" />
    <component-filter name="com.tencent.mm/com.tencent.mm.plugin.game.ui.GameRankUI" />
    <component-filter name="com.tencent.mm/com.tencent.mm.plugin.game.ui.GameRegionSelectUI" />
    <component-filter name="com.tencent.mm/com.tencent.mm.plugin.game.ui.GameSearchUI" />
    <component-filter name="com.tencent.mm/com.tencent.mm.plugin.game.ui.GameSettingsUI" />
    <component-filter name="com.tencent.mm/com.tencent.mm.plugin.qqmail.stub.QQMailStubProxyUI" />
    <component-filter name="com.tencent.mm/com.tencent.mm.plugin.qqmail.ui.AttachDownloadPage" />
    <component-filter name="com.tencent.mm/com.tencent.mm.plugin.qqmail.ui.ComposeUI" />
    <component-filter name="com.tencent.mm/com.tencent.mm.plugin.qqmail.ui.CompressPreviewUI" />
    <component-filter name="com.tencent.mm/com.tencent.mm.plugin.qqmail.ui.MailAddrListUI" />
    <component-filter name="com.tencent.mm/com.tencent.mm.plugin.qqmail.ui.MailAddrProfileUI" />
    <component-filter name="com.tencent.mm/com.tencent.mm.plugin.qqmail.ui.MailImageDownloadUI" />
    <component-filter name="com.tencent.mm/com.tencent.mm.plugin.qqmail.ui.MailWebViewUI" />
    <component-filter name="com.tencent.mm/com.tencent.mm.plugin.qqmail.ui.ReadMailUI" />
    <component-filter name="com.tencent.mm/com.tencent.mm.plugin.shake.shakemedia.ui.ShakeTVDetailUI" />
    <component-filter name="com.tencent.mm/com.tencent.mm.plugin.shake.ui.ShakeItemListUI" />
    <component-filter name="com.tencent.mm/com.tencent.mm.plugin.shake.ui.ShakeMsgListUI" />
    <component-filter name="com.tencent.mm/com.tencent.mm.plugin.shake.ui.ShakeNewYearReportUI" />
    <component-filter name="com.tencent.mm/com.tencent.mm.plugin.shake.ui.ShakePersonalInfoUI" />
    <component-filter name="com.tencent.mm/com.tencent.mm.plugin.shake.ui.ShakeReportUI" />
    <component-filter name="com.tencent.mm/com.tencent.mm.plugin.shake.ui.ShakeSayHiListUI" />
    <component-filter name="com.tencent.mm/com.tencent.mm.plugin.shake.ui.ShakeTvHistoryListUI" />
    <component-filter name="com.tencent.mm/com.tencent.mm.plugin.shake.ui.TVInfoUI" />
    <component-filter name="com.tencent.mm/com.tencent.mm.plugin.sport.service.SportService" />
    <component-filter name="com.tencent.mm/com.tencent.mm.plugin.subapp.jdbiz.JDRemindDialog" />
    <component-filter name="com.tencent.mm/com.tencent.mm.plugin.wear.model.service.WearDataLayerService" />
    <component-filter name="com.tencent.mm/com.tencent.mm.plugin.webview.ui.tools.game.GameChattingRoomWebViewUI" />
    <component-filter name="com.tencent.mm/com.tencent.mm.plugin.webview.ui.tools.game.GameWebViewUI" />
    <component-filter name="com.tencent.mm/com.tencent.mm.plugin.webview.ui.tools.game.H5GameWebViewUI" />
    <component-filter name="com.tencent.mm/com.tencent.mm.sandbox.monitor.CrashUploadAlarmReceiver" />
    <component-filter name="com.tencent.mm/com.tencent.mm.sandbox.updater.AppInstallerUI" />
    <component-filter name="com.tencent.mm/com.tencent.mm.sandbox.updater.AppUpdaterUI" />
    <component-filter name="com.tencent.mm/com.tencent.mm.sandbox.updater.UpdaterService" />
    <component-filter name="com.tencent.mm/com.tencent.mm.ui.account.BindFacebookUI" />
    <component-filter name="com.tencent.mm/com.tencent.mm.ui.account.FacebookAuthUI" />
    <component-filter name="com.tencent.mm/com.tencent.mm.ui.account.FacebookFriendUI" />
    <component-filter name="com.tencent.mm/com.tencent.mm.ui.account.FacebookLoginUI" />
    <component-filter name="com.tencent.mm/com.tencent.mm.ui.account.RegByFacebookSetPwdUI" />
    <component-filter name="com.tencent.mm/com.tencent.mm.ui.bindgooglecontact.BindGoogleContactIntroUI" />
    <component-filter name="com.tencent.mm/com.tencent.mm.ui.bindgooglecontact.BindGoogleContactUI" />
    <component-filter name="com.tencent.mm/com.tencent.mm.ui.bindgooglecontact.GoogleFriendUI" />
    <component-filter name="com.tencent.mm/com.tencent.mm.ui.bindlinkedin.BindLinkedInUI" />
    <component-filter name="com.tencent.mm/com.tencent.mm.ui.friend.InviteFacebookFriendsUI" />
    <component-filter name="com.tencent.mm/com.tencent.recovery.wx.service.WXRecoveryUploadService" />
    <component-filter name="com.tencent.mm/com.tencent.tmassistantsdk.downloadservice.TMAssistantDownloadSDKService" />
    <component-filter name="com.xiaomi.o2o/com.tencent.mm.sdk.channel.MMessage$Receiver" />
    <component-filter name="com.xiaomi.o2o/com.tencent.mm.sdk.plugin.MMPluginOAuth$Receiver" />
</broadcast>
<activity block="true" log="false">
    <component-filter name="com.tencent.mm/com.tencent.mm.booter.InstallReceiver" />
    <component-filter name="com.tencent.mm/com.tencent.mm.booter.cache.CacheService" />
    <component-filter name="com.tencent.mm/com.tencent.mm.crash.CrashUploaderService" />
    <component-filter name="com.tencent.mm/com.tencent.mm.modelfriend.AddrBookObserver$AddrBookService" />
    <component-filter name="com.tencent.mm/com.tencent.mm.plugin.accountsync.model.AccountAuthenticatorService" />
    <component-filter name="com.tencent.mm/com.tencent.mm.plugin.accountsync.model.ContactsSyncService" />
    <component-filter name="com.tencent.mm/com.tencent.mm.plugin.accountsync.ui.ShareToFacebookRedirectUI" />
    <component-filter name="com.tencent.mm/com.tencent.mm.plugin.appbrand.task.AppBrandTaskPreloadReceiver" />
    <component-filter name="com.tencent.mm/com.tencent.mm.plugin.appbrand.task.AppBrandTaskPreloadReceiver1" />
    <component-filter name="com.tencent.mm/com.tencent.mm.plugin.appbrand.task.AppBrandTaskPreloadReceiver2" />
    <component-filter name="com.tencent.mm/com.tencent.mm.plugin.appbrand.task.AppBrandTaskPreloadReceiver3" />
    <component-filter name="com.tencent.mm/com.tencent.mm.plugin.appbrand.task.AppBrandTaskPreloadReceiver4" />
    <component-filter name="com.tencent.mm/com.tencent.mm.plugin.backup.backuppcmodel.BackupPcService" />
    <component-filter name="com.tencent.mm/com.tencent.mm.plugin.backup.bakoldlogic.bakoldmodel.BakOldUSBService" />
    <component-filter name="com.tencent.mm/com.tencent.mm.plugin.backup.bakoldlogic.bakoldmovemodel.MoveService" />
    <component-filter name="com.tencent.mm/com.tencent.mm.plugin.backup.bakoldlogic.bakoldpcmodel.BakchatPcUsbService" />
    <component-filter name="com.tencent.mm/com.tencent.mm.plugin.exdevice.ui.ExdeviceConnectWifiUI" />
    <component-filter name="com.tencent.mm/com.tencent.mm.plugin.facedetect.service.FaceDetectProcessService" />
    <component-filter name="com.tencent.mm/com.tencent.mm.plugin.facedetect.service.FaceUploadVideoService" />
    <component-filter name="com.tencent.mm/com.tencent.mm.plugin.freewifi.ui.FreeWifiActivateAuthStateUI" />
    <component-filter name="com.tencent.mm/com.tencent.mm.plugin.freewifi.ui.FreeWifiAuthStateUI" />
    <component-filter name="com.tencent.mm/com.tencent.mm.plugin.freewifi.ui.FreeWifiCopyPwdUI" />
    <component-filter name="com.tencent.mm/com.tencent.mm.plugin.freewifi.ui.FreeWifiEntryUI" />
    <component-filter name="com.tencent.mm/com.tencent.mm.plugin.freewifi.ui.FreeWifiErrorUI" />
    <component-filter name="com.tencent.mm/com.tencent.mm.plugin.freewifi.ui.FreeWifiFrontPageUI" />
    <component-filter name="com.tencent.mm/com.tencent.mm.plugin.freewifi.ui.FreeWifiIntroductionUI" />
    <component-filter name="com.tencent.mm/com.tencent.mm.plugin.freewifi.ui.FreeWifiMIGNoAuthStateUI" />
    <component-filter name="com.tencent.mm/com.tencent.mm.plugin.freewifi.ui.FreeWifiManufacturerLoadingUI" />
    <component-filter name="com.tencent.mm/com.tencent.mm.plugin.freewifi.ui.FreeWifiNetCheckUI" />
    <component-filter name="com.tencent.mm/com.tencent.mm.plugin.freewifi.ui.FreeWifiNoWifiUI" />
    <component-filter name="com.tencent.mm/com.tencent.mm.plugin.freewifi.ui.FreeWifiOwnerUI" />
    <component-filter name="com.tencent.mm/com.tencent.mm.plugin.freewifi.ui.FreeWifiPcUI" />
    <component-filter name="com.tencent.mm/com.tencent.mm.plugin.freewifi.ui.FreeWifiSuccUI" />
    <component-filter name="com.tencent.mm/com.tencent.mm.plugin.freewifi.ui.FreeWifiSuccWebViewUI" />
    <component-filter name="com.tencent.mm/com.tencent.mm.plugin.freewifi.ui.FreeWifiTestActivity" />
    <component-filter name="com.tencent.mm/com.tencent.mm.plugin.freewifi.ui.FreewifiActivateWeChatNoAuthStateUI" />
    <component-filter name="com.tencent.mm/com.tencent.mm.plugin.freewifi.ui.FreewifiWeChatNoAuthStateUI" />
    <component-filter name="com.tencent.mm/com.tencent.mm.plugin.freewifi.ui.ProtocolThreeOneUI" />
    <component-filter name="com.tencent.mm/com.tencent.mm.plugin.freewifi.ui.ProtocolThreeThreeUI" />
    <component-filter name="com.tencent.mm/com.tencent.mm.plugin.freewifi.ui.ProtocolThreeTwoUI" />
    <component-filter name="com.tencent.mm/com.tencent.mm.plugin.game.gamewebview.ipc.GameWebViewMainProcessService" />
    <component-filter name="com.tencent.mm/com.tencent.mm.plugin.game.gamewebview.ui.GameIpcProxyUI" />
    <component-filter name="com.tencent.mm/com.tencent.mm.plugin.game.gamewebview.ui.GameWebViewUI" />
    <component-filter name="com.tencent.mm/com.tencent.mm.plugin.game.ui.AuthorizedGameListUI" />
    <component-filter name="com.tencent.mm/com.tencent.mm.plugin.game.ui.CreateOrJoinChatroomUI" />
    <component-filter name="com.tencent.mm/com.tencent.mm.plugin.game.ui.GameCategoryUI" />
    <component-filter name="com.tencent.mm/com.tencent.mm.plugin.game.ui.GameCenterUI" />
    <component-filter name="com.tencent.mm/com.tencent.mm.plugin.game.ui.GameCenterUI2" />
    <component-filter name="com.tencent.mm/com.tencent.mm.plugin.game.ui.GameDetailInfoUI" />
    <component-filter name="com.tencent.mm/com.tencent.mm.plugin.game.ui.GameDetailRankLikedUI" />
    <component-filter name="com.tencent.mm/com.tencent.mm.plugin.game.ui.GameDetailRankUI" />
    <component-filter name="com.tencent.mm/com.tencent.mm.plugin.game.ui.GameDetailUI" />
    <component-filter name="com.tencent.mm/com.tencent.mm.plugin.game.ui.GameDetailUI2" />
    <component-filter name="com.tencent.mm/com.tencent.mm.plugin.game.ui.GameDownloadTipsUI" />
    <component-filter name="com.tencent.mm/com.tencent.mm.plugin.game.ui.GameGalleryUI" />
    <component-filter name="com.tencent.mm/com.tencent.mm.plugin.game.ui.GameGestureGalleryUI" />
    <component-filter name="com.tencent.mm/com.tencent.mm.plugin.game.ui.GameIndexUI" />
    <component-filter name="com.tencent.mm/com.tencent.mm.plugin.game.ui.GameLibraryUI" />
    <component-filter name="com.tencent.mm/com.tencent.mm.plugin.game.ui.GameMD5CheckUI" />
    <component-filter name="com.tencent.mm/com.tencent.mm.plugin.game.ui.GameMessageUI" />
    <component-filter name="com.tencent.mm/com.tencent.mm.plugin.game.ui.GameNewIntroductionUI" />
    <component-filter name="com.tencent.mm/com.tencent.mm.plugin.game.ui.GameRankMsgUI" />
    <component-filter name="com.tencent.mm/com.tencent.mm.plugin.game.ui.GameRankUI" />
    <component-filter name="com.tencent.mm/com.tencent.mm.plugin.game.ui.GameRegionSelectUI" />
    <component-filter name="com.tencent.mm/com.tencent.mm.plugin.game.ui.GameSearchUI" />
    <component-filter name="com.tencent.mm/com.tencent.mm.plugin.game.ui.GameSettingsUI" />
    <component-filter name="com.tencent.mm/com.tencent.mm.plugin.qqmail.stub.QQMailStubProxyUI" />
    <component-filter name="com.tencent.mm/com.tencent.mm.plugin.qqmail.ui.AttachDownloadPage" />
    <component-filter name="com.tencent.mm/com.tencent.mm.plugin.qqmail.ui.ComposeUI" />
    <component-filter name="com.tencent.mm/com.tencent.mm.plugin.qqmail.ui.CompressPreviewUI" />
    <component-filter name="com.tencent.mm/com.tencent.mm.plugin.qqmail.ui.MailAddrListUI" />
    <component-filter name="com.tencent.mm/com.tencent.mm.plugin.qqmail.ui.MailAddrProfileUI" />
    <component-filter name="com.tencent.mm/com.tencent.mm.plugin.qqmail.ui.MailImageDownloadUI" />
    <component-filter name="com.tencent.mm/com.tencent.mm.plugin.qqmail.ui.MailWebViewUI" />
    <component-filter name="com.tencent.mm/com.tencent.mm.plugin.qqmail.ui.ReadMailUI" />
    <component-filter name="com.tencent.mm/com.tencent.mm.plugin.shake.shakemedia.ui.ShakeTVDetailUI" />
    <component-filter name="com.tencent.mm/com.tencent.mm.plugin.shake.ui.ShakeItemListUI" />
    <component-filter name="com.tencent.mm/com.tencent.mm.plugin.shake.ui.ShakeMsgListUI" />
    <component-filter name="com.tencent.mm/com.tencent.mm.plugin.shake.ui.ShakeNewYearReportUI" />
    <component-filter name="com.tencent.mm/com.tencent.mm.plugin.shake.ui.ShakePersonalInfoUI" />
    <component-filter name="com.tencent.mm/com.tencent.mm.plugin.shake.ui.ShakeReportUI" />
    <component-filter name="com.tencent.mm/com.tencent.mm.plugin.shake.ui.ShakeSayHiListUI" />
    <component-filter name="com.tencent.mm/com.tencent.mm.plugin.shake.ui.ShakeTvHistoryListUI" />
    <component-filter name="com.tencent.mm/com.tencent.mm.plugin.shake.ui.TVInfoUI" />
    <component-filter name="com.tencent.mm/com.tencent.mm.plugin.sport.service.SportService" />
    <component-filter name="com.tencent.mm/com.tencent.mm.plugin.subapp.jdbiz.JDRemindDialog" />
    <component-filter name="com.tencent.mm/com.tencent.mm.plugin.wear.model.service.WearDataLayerService" />
    <component-filter name="com.tencent.mm/com.tencent.mm.plugin.webview.ui.tools.game.GameChattingRoomWebViewUI" />
    <component-filter name="com.tencent.mm/com.tencent.mm.plugin.webview.ui.tools.game.GameWebViewUI" />
    <component-filter name="com.tencent.mm/com.tencent.mm.plugin.webview.ui.tools.game.H5GameWebViewUI" />
    <component-filter name="com.tencent.mm/com.tencent.mm.sandbox.monitor.CrashUploadAlarmReceiver" />
    <component-filter name="com.tencent.mm/com.tencent.mm.sandbox.updater.AppInstallerUI" />
    <component-filter name="com.tencent.mm/com.tencent.mm.sandbox.updater.AppUpdaterUI" />
    <component-filter name="com.tencent.mm/com.tencent.mm.sandbox.updater.UpdaterService" />
    <component-filter name="com.tencent.mm/com.tencent.mm.ui.account.BindFacebookUI" />
    <component-filter name="com.tencent.mm/com.tencent.mm.ui.account.FacebookAuthUI" />
    <component-filter name="com.tencent.mm/com.tencent.mm.ui.account.FacebookFriendUI" />
    <component-filter name="com.tencent.mm/com.tencent.mm.ui.account.FacebookLoginUI" />
    <component-filter name="com.tencent.mm/com.tencent.mm.ui.account.RegByFacebookSetPwdUI" />
    <component-filter name="com.tencent.mm/com.tencent.mm.ui.bindgooglecontact.BindGoogleContactIntroUI" />
    <component-filter name="com.tencent.mm/com.tencent.mm.ui.bindgooglecontact.BindGoogleContactUI" />
    <component-filter name="com.tencent.mm/com.tencent.mm.ui.bindgooglecontact.GoogleFriendUI" />
    <component-filter name="com.tencent.mm/com.tencent.mm.ui.bindlinkedin.BindLinkedInUI" />
    <component-filter name="com.tencent.mm/com.tencent.mm.ui.friend.InviteFacebookFriendsUI" />
    <component-filter name="com.tencent.mm/com.tencent.recovery.wx.service.WXRecoveryUploadService" />
    <component-filter name="com.tencent.mm/com.tencent.tmassistantsdk.downloadservice.TMAssistantDownloadSDKService" />
    <component-filter name="com.xiaomi.o2o/com.tencent.mm.sdk.channel.MMessage$Receiver" />
    <component-filter name="com.xiaomi.o2o/com.tencent.mm.sdk.plugin.MMPluginOAuth$Receiver" />
</activity>
</rules>